<?xml version="1.0" encoding="UTF-8"?>

<!-- generated on 02/25/19 09:55:06 by Eclipse SUMO GUI Version 1.0.1
<configuration xmlns:xsi="http://www.w3.org/2001/XMLSchema-instance" xsi:noNamespaceSchemaLocation="http://sumo.dlr.de/xsd/sumoConfiguration.xsd">

    <input>
        <net-file value="c:\users\isaia\onedrive\documents\github\gym-sumo-envs\gym_traffic\envs\config\T-Intersection\tIntersection.net.xml"/>
        <route-files value="tmp.rou.xml"/>
        <additional-files value="c:\users\isaia\onedrive\documents\github\gym-sumo-envs\gym_traffic\envs\config\T-Intersection\tIntersection.add.xml"/>
    </input>

    <traci_server>
        <remote-port value="49858"/>
    </traci_server>

    <gui_only>
        <quit-on-end value="true"/>
        <start value="true"/>
    </gui_only>

</configuration>
-->

<meandata xmlns:xsi="http://www.w3.org/2001/XMLSchema-instance" xsi:noNamespaceSchemaLocation="http://sumo.dlr.de/xsd/meandata_file.xsd">
    <interval begin="0.00" end="20.00" id="Noise Data">
        <edge id="EW_1" sampledSeconds="61.57" noise="70.91" traveltime="13.63"/>
        <edge id="EW_2" sampledSeconds="0.37" noise="52.62" traveltime="14.14"/>
        <edge id="NS_1" sampledSeconds="64.48" noise="71.22" traveltime="16.59"/>
        <edge id="SN_2" sampledSeconds="3.97" noise="59.96" traveltime="11.16"/>
        <edge id="WE_1" sampledSeconds="59.94" noise="71.63" traveltime="12.71"/>
        <edge id="WE_2" sampledSeconds="2.34" noise="59.60" traveltime="10.08"/>
    </interval>
    <interval begin="20.00" end="37.00" id="Noise Data">
        <edge id="EW_1" sampledSeconds="122.96" noise="73.42" traveltime="19.07"/>
        <edge id="EW_2" sampledSeconds="26.88" noise="70.26" traveltime="7.87"/>
        <edge id="NS_1" sampledSeconds="121.42" noise="71.01" traveltime="32.19"/>
        <edge id="SN_2" sampledSeconds="45.02" noise="72.86" traveltime="7.35"/>
        <edge id="WE_1" sampledSeconds="74.50" noise="73.50" traveltime="11.95"/>
        <edge id="WE_2" sampledSeconds="36.43" noise="69.18" traveltime="7.88"/>
    </interval>
</meandata>
