<?xml version="1.0" encoding="UTF-8"?>

<!-- generated on 03/04/19 14:10:59 by Eclipse SUMO GUI Version 1.0.1
<configuration xmlns:xsi="http://www.w3.org/2001/XMLSchema-instance" xsi:noNamespaceSchemaLocation="http://sumo.dlr.de/xsd/sumoConfiguration.xsd">

    <input>
        <net-file value="c:\users\isaia\onedrive\documents\github\gym-sumo-envs\gym_traffic\envs\config\T-Intersection\tIntersection.net.xml"/>
        <route-files value="tmp.rou.xml"/>
        <additional-files value="c:\users\isaia\onedrive\documents\github\gym-sumo-envs\gym_traffic\envs\config\T-Intersection\tIntersection.add.xml"/>
    </input>

    <traci_server>
        <remote-port value="52691"/>
    </traci_server>

    <gui_only>
        <quit-on-end value="true"/>
        <start value="true"/>
    </gui_only>

</configuration>
-->

<meandata xmlns:xsi="http://www.w3.org/2001/XMLSchema-instance" xsi:noNamespaceSchemaLocation="http://sumo.dlr.de/xsd/meandata_file.xsd">
    <interval begin="0.00" end="20.00" id="Noise Data">
        <edge id="EW_1" sampledSeconds="61.57" noise="70.91" traveltime="13.63"/>
        <edge id="EW_2" sampledSeconds="0.37" noise="52.62" traveltime="14.14"/>
        <edge id="NS_1" sampledSeconds="64.48" noise="71.22" traveltime="16.59"/>
        <edge id="SN_2" sampledSeconds="3.97" noise="59.96" traveltime="11.16"/>
        <edge id="WE_1" sampledSeconds="59.94" noise="71.63" traveltime="12.71"/>
        <edge id="WE_2" sampledSeconds="2.34" noise="59.60" traveltime="10.08"/>
    </interval>
    <interval begin="20.00" end="40.00" id="Noise Data">
        <edge id="EW_1" sampledSeconds="149.96" noise="73.47" traveltime="19.95"/>
        <edge id="EW_2" sampledSeconds="32.18" noise="70.43" traveltime="7.85"/>
        <edge id="NS_1" sampledSeconds="149.42" noise="70.76" traveltime="35.72"/>
        <edge id="SN_2" sampledSeconds="49.02" noise="72.29" traveltime="7.31"/>
        <edge id="WE_1" sampledSeconds="89.50" noise="73.52" traveltime="12.26"/>
        <edge id="WE_2" sampledSeconds="42.43" noise="68.95" traveltime="7.82"/>
    </interval>
    <interval begin="40.00" end="57.00" id="Noise Data">
        <edge id="EW_1" sampledSeconds="158.37" noise="73.64" traveltime="22.20"/>
        <edge id="EW_2" sampledSeconds="30.15" noise="69.09" traveltime="7.88"/>
        <edge id="NS_1" sampledSeconds="165.64" noise="68.66" traveltime="71.46"/>
        <edge id="SN_2" sampledSeconds="34.80" noise="71.23" traveltime="7.58"/>
        <edge id="WE_1" sampledSeconds="84.68" noise="73.01" traveltime="14.85"/>
        <edge id="WE_2" sampledSeconds="36.29" noise="70.16" traveltime="7.44"/>
    </interval>
</meandata>
